selenium_clay/__init__.py
selenium_clay-0.0.0.dist-info/METADATA
selenium_clay-0.0.0.dist-info/WHEEL
selenium_clay-0.0.0.dist-info/top_level.txt
selenium_clay-0.0.0.dist-info/RECORD
